{"v":"4.10.1","fr":29.9700012207031,"ip":0,"op":180.00000733155,"w":1280,"h":1280,"nm":"首頁動畫1","ddd":0,"assets":[{"id":"image_0","w":14,"h":19,"u":"images/","p":"img_0.png"},{"id":"image_1","w":92,"h":87,"u":"images/","p":"img_1.png"},{"id":"image_2","w":34,"h":34,"u":"images/","p":"img_2.png"},{"id":"image_3","w":5,"h":5,"u":"images/","p":"img_3.png"},{"id":"image_4","w":75,"h":42,"u":"images/","p":"img_4.png"},{"id":"image_5","w":81,"h":85,"u":"images/","p":"img_5.png"},{"id":"image_6","w":98,"h":112,"u":"images/","p":"img_6.png"},{"id":"image_7","w":825,"h":499,"u":"images/","p":"img_7.png"},{"id":"image_8","w":40,"h":20,"u":"images/","p":"img_8.png"},{"id":"image_9","w":73,"h":21,"u":"images/","p":"img_9.png"},{"id":"image_10","w":29,"h":43,"u":"images/","p":"img_10.png"},{"id":"image_11","w":29,"h":43,"u":"images/","p":"img_11.png"},{"id":"comp_0","layers":[{"ddd":0,"ind":1,"ty":2,"nm":"豬","parent":2,"refId":"image_0","sr":1,"ks":{"o":{"a":1,"k":[{"i":{"x":[0.833],"y":[0.833]},"o":{"x":[0.167],"y":[0.167]},"n":["0p833_0p833_0p167_0p167"],"t":0,"s":[29],"e":[79]},{"i":{"x":[0.833],"y":[0.833]},"o":{"x":[0.167],"y":[0.167]},"n":["0p833_0p833_0p167_0p167"],"t":60,"s":[79],"e":[79]},{"i":{"x":[0.833],"y":[0.833]},"o":{"x":[0.167],"y":[0.167]},"n":["0p833_0p833_0p167_0p167"],"t":64,"s":[79],"e":[29]},{"i":{"x":[0.833],"y":[0.833]},"o":{"x":[0.167],"y":[0.167]},"n":["0p833_0p833_0p167_0p167"],"t":65,"s":[29],"e":[29]},{"i":{"x":[0.833],"y":[0.833]},"o":{"x":[0.167],"y":[0.167]},"n":["0p833_0p833_0p167_0p167"],"t":68,"s":[29],"e":[79]},{"i":{"x":[0.833],"y":[0.833]},"o":{"x":[0.167],"y":[0.167]},"n":["0p833_0p833_0p167_0p167"],"t":69,"s":[79],"e":[79]},{"i":{"x":[0.833],"y":[0.833]},"o":{"x":[0.167],"y":[0.167]},"n":["0p833_0p833_0p167_0p167"],"t":72,"s":[79],"e":[29]},{"i":{"x":[0.833],"y":[0.833]},"o":{"x":[0.167],"y":[0.167]},"n":["0p833_0p833_0p167_0p167"],"t":73,"s":[29],"e":[29]},{"i":{"x":[0.833],"y":[0.833]},"o":{"x":[0.167],"y":[0.167]},"n":["0p833_0p833_0p167_0p167"],"t":76,"s":[29],"e":[79]},{"i":{"x":[0.833],"y":[0.833]},"o":{"x":[0.167],"y":[0.167]},"n":["0p833_0p833_0p167_0p167"],"t":77,"s":[79],"e":[75]},{"i":{"x":[0.833],"y":[0.833]},"o":{"x":[0.167],"y":[0.167]},"n":["0p833_0p833_0p167_0p167"],"t":80,"s":[75],"e":[29]},{"i":{"x":[0.833],"y":[0.833]},"o":{"x":[0.167],"y":[0.167]},"n":["0p833_0p833_0p167_0p167"],"t":81,"s":[29],"e":[29]},{"i":{"x":[0.833],"y":[0.833]},"o":{"x":[0.167],"y":[0.167]},"n":["0p833_0p833_0p167_0p167"],"t":84,"s":[29],"e":[79]},{"i":{"x":[0.833],"y":[0.833]},"o":{"x":[0.167],"y":[0.167]},"n":["0p833_0p833_0p167_0p167"],"t":85,"s":[79],"e":[79]},{"i":{"x":[0.833],"y":[0.833]},"o":{"x":[0.167],"y":[0.167]},"n":["0p833_0p833_0p167_0p167"],"t":130,"s":[79],"e":[0]},{"t":150.000006109625}],"ix":11},"r":{"a":0,"k":0,"ix":10},"p":{"a":1,"k":[{"i":{"x":0.833,"y":0.833},"o":{"x":0.167,"y":0.167},"n":"0p833_0p833_0p167_0p167","t":0,"s":[82.322,29.39,0],"e":[82.322,29.39,0],"to":[-4.27083349227905,-8.91666698455811,0],"ti":[1.49403011798859,3.11924338340759,0]},{"i":{"x":0.833,"y":0.833},"o":{"x":0.167,"y":0.167},"n":"0p833_0p833_0p167_0p167","t":34,"s":[82.322,29.39,0],"e":[65.697,16.14,0],"to":[-4.27083349227905,-8.91666698455811,0],"ti":[4.39583349227905,0.10416666418314,0]},{"i":{"x":0.833,"y":0.833},"o":{"x":0.167,"y":0.167},"n":"0p833_0p833_0p167_0p167","t":46,"s":[65.697,16.14,0],"e":[65.697,16.14,0],"to":[0,0,0],"ti":[0,0,0]},{"i":{"x":0.833,"y":0.833},"o":{"x":0.167,"y":0.167},"n":"0p833_0p833_0p167_0p167","t":52,"s":[65.697,16.14,0],"e":[65.697,16.14,0],"to":[0,0,0],"ti":[0,0,0]},{"t":150.000006109625}],"ix":2},"a":{"a":0,"k":[7,9.5,0],"ix":1},"s":{"a":0,"k":[100,100,100],"ix":6}},"ao":0,"hasMask":true,"masksProperties":[{"inv":false,"mode":"a","pt":{"a":1,"k":[{"i":{"x":0.833,"y":0.833},"o":{"x":0.167,"y":0.167},"n":"0p833_0p833_0p167_0p167","t":0,"s":[{"i":[[0,0],[0,0],[0,0],[0,0]],"o":[[0,0],[0,0],[0,0],[0,0]],"v":[[-26.029,-16.888],[-26.279,1.362],[0.471,9.362],[0.221,-8.138]],"c":true}],"e":[{"i":[[0,0],[0,0],[0,0],[0,0]],"o":[[0,0],[0,0],[0,0],[0,0]],"v":[[-23.122,-10.981],[-27.325,5.399],[0.286,8.464],[1.036,-9.036]],"c":true}]},{"i":{"x":0.833,"y":0.833},"o":{"x":0.167,"y":0.167},"n":"0p833_0p833_0p167_0p167","t":34,"s":[{"i":[[0,0],[0,0],[0,0],[0,0]],"o":[[0,0],[0,0],[0,0],[0,0]],"v":[[-23.122,-10.981],[-27.325,5.399],[0.286,8.464],[1.036,-9.036]],"c":true}],"e":[{"i":[[0,0],[0,0],[0,0],[0,0]],"o":[[0,0],[0,0],[0,0],[0,0]],"v":[[-18.86,-8.927],[-23.562,7.625],[9.351,19.574],[9.073,-1.676]],"c":true}]},{"i":{"x":0.833,"y":0.833},"o":{"x":0.167,"y":0.167},"n":"0p833_0p833_0p167_0p167","t":41,"s":[{"i":[[0,0],[0,0],[0,0],[0,0]],"o":[[0,0],[0,0],[0,0],[0,0]],"v":[[-18.86,-8.927],[-23.562,7.625],[9.351,19.574],[9.073,-1.676]],"c":true}],"e":[{"i":[[0,0],[0,0],[0,0],[0,0]],"o":[[0,0],[0,0],[0,0],[0,0]],"v":[[-14.598,-6.874],[-19.8,9.851],[16.916,23.185],[17.111,5.685]],"c":true}]},{"i":{"x":0.833,"y":0.833},"o":{"x":0.167,"y":0.167},"n":"0p833_0p833_0p167_0p167","t":48,"s":[{"i":[[0,0],[0,0],[0,0],[0,0]],"o":[[0,0],[0,0],[0,0],[0,0]],"v":[[-14.598,-6.874],[-19.8,9.851],[16.916,23.185],[17.111,5.685]],"c":true}],"e":[{"i":[[0,0],[0,0],[0,0],[0,0]],"o":[[0,0],[0,0],[0,0],[0,0]],"v":[[-10.279,-3.888],[-10.529,14.362],[16.221,22.362],[15.971,4.862]],"c":true}]},{"t":150.000006109625}],"ix":1},"o":{"a":0,"k":100,"ix":3},"x":{"a":0,"k":0,"ix":4},"nm":"Mask 1"}],"ip":0,"op":180.00000733155,"st":0,"bm":0},{"ddd":0,"ind":2,"ty":2,"nm":"電視雲","refId":"image_1","sr":1,"ks":{"o":{"a":1,"k":[{"i":{"x":[0.833],"y":[0.833]},"o":{"x":[0.167],"y":[0.167]},"n":["0p833_0p833_0p167_0p167"],"t":0,"s":[11],"e":[0]},{"i":{"x":[0.833],"y":[0.833]},"o":{"x":[0.167],"y":[0.167]},"n":["0p833_0p833_0p167_0p167"],"t":27,"s":[0],"e":[100]},{"i":{"x":[0.833],"y":[0.833]},"o":{"x":[0.167],"y":[0.167]},"n":["0p833_0p833_0p167_0p167"],"t":30,"s":[100],"e":[100]},{"i":{"x":[0.833],"y":[0.833]},"o":{"x":[0.167],"y":[0.167]},"n":["0p833_0p833_0p167_0p167"],"t":60,"s":[100],"e":[100]},{"i":{"x":[0.833],"y":[0.833]},"o":{"x":[0.167],"y":[0.167]},"n":["0p833_0p833_0p167_0p167"],"t":64,"s":[100],"e":[50]},{"i":{"x":[0.833],"y":[0.833]},"o":{"x":[0.167],"y":[0.167]},"n":["0p833_0p833_0p167_0p167"],"t":65,"s":[50],"e":[50]},{"i":{"x":[0.833],"y":[0.833]},"o":{"x":[0.167],"y":[0.167]},"n":["0p833_0p833_0p167_0p167"],"t":68,"s":[50],"e":[100]},{"i":{"x":[0.833],"y":[0.833]},"o":{"x":[0.167],"y":[0.167]},"n":["0p833_0p833_0p167_0p167"],"t":69,"s":[100],"e":[100]},{"i":{"x":[0.833],"y":[0.833]},"o":{"x":[0.167],"y":[0.167]},"n":["0p833_0p833_0p167_0p167"],"t":72,"s":[100],"e":[50]},{"i":{"x":[0.833],"y":[0.833]},"o":{"x":[0.167],"y":[0.167]},"n":["0p833_0p833_0p167_0p167"],"t":73,"s":[50],"e":[50]},{"i":{"x":[0.833],"y":[0.833]},"o":{"x":[0.167],"y":[0.167]},"n":["0p833_0p833_0p167_0p167"],"t":76,"s":[50],"e":[100]},{"i":{"x":[0.833],"y":[0.833]},"o":{"x":[0.167],"y":[0.167]},"n":["0p833_0p833_0p167_0p167"],"t":77,"s":[100],"e":[96]},{"i":{"x":[0.833],"y":[0.833]},"o":{"x":[0.167],"y":[0.167]},"n":["0p833_0p833_0p167_0p167"],"t":80,"s":[96],"e":[50]},{"i":{"x":[0.833],"y":[0.833]},"o":{"x":[0.167],"y":[0.167]},"n":["0p833_0p833_0p167_0p167"],"t":81,"s":[50],"e":[50]},{"i":{"x":[0.833],"y":[0.833]},"o":{"x":[0.167],"y":[0.167]},"n":["0p833_0p833_0p167_0p167"],"t":84,"s":[50],"e":[100]},{"i":{"x":[0.833],"y":[0.833]},"o":{"x":[0.167],"y":[0.167]},"n":["0p833_0p833_0p167_0p167"],"t":85,"s":[100],"e":[100]},{"i":{"x":[0.833],"y":[0.833]},"o":{"x":[0.167],"y":[0.167]},"n":["0p833_0p833_0p167_0p167"],"t":130,"s":[100],"e":[0]},{"t":150.000006109625}],"ix":11},"r":{"a":0,"k":0,"ix":10},"p":{"a":0,"k":[689.457,410.498,0],"ix":2},"a":{"a":0,"k":[46,43.5,0],"ix":1},"s":{"a":0,"k":[100,100,100],"ix":6}},"ao":0,"ip":0,"op":180.00000733155,"st":0,"bm":0},{"ddd":0,"ind":3,"ty":2,"nm":"偵測器","refId":"image_2","sr":1,"ks":{"o":{"a":0,"k":100,"ix":11},"r":{"a":1,"k":[{"i":{"x":[0.833],"y":[0.833]},"o":{"x":[0.167],"y":[0.167]},"n":["0p833_0p833_0p167_0p167"],"t":0,"s":[0],"e":[27]},{"i":{"x":[0.833],"y":[0.833]},"o":{"x":[0.167],"y":[0.167]},"n":["0p833_0p833_0p167_0p167"],"t":45,"s":[27],"e":[0]},{"t":90.0000036657751}],"ix":10,"x":"var $bm_rt;\n$bm_rt = loopOut('cycle');"},"p":{"a":0,"k":[868.564,379.4,0],"ix":2},"a":{"a":0,"k":[16.799,16.799,0],"ix":1},"s":{"a":0,"k":[100,100,100],"ix":6}},"ao":0,"ip":0,"op":180.00000733155,"st":0,"bm":0},{"ddd":0,"ind":4,"ty":2,"nm":"泳池男","refId":"image_3","sr":1,"ks":{"o":{"a":0,"k":100,"ix":11},"r":{"a":0,"k":0,"ix":10},"p":{"a":1,"k":[{"i":{"x":0.833,"y":0.833},"o":{"x":0.167,"y":0.167},"n":"0p833_0p833_0p167_0p167","t":0,"s":[619.454,374.746,0],"e":[624.204,374.496,0],"to":[0.79166668653488,-0.04166666790843,0],"ti":[0,0,0]},{"i":{"x":0.833,"y":0.833},"o":{"x":0.167,"y":0.167},"n":"0p833_0p833_0p167_0p167","t":45,"s":[624.204,374.496,0],"e":[619.454,374.746,0],"to":[0,0,0],"ti":[0.79166668653488,-0.04166666790843,0]},{"t":90.0000036657751}],"ix":2,"x":"var $bm_rt;\n$bm_rt = loopOut('cycle');"},"a":{"a":0,"k":[2.493,2.392,0],"ix":1},"s":{"a":0,"k":[100,100,100],"ix":6}},"ao":0,"ip":0,"op":180.00000733155,"st":0,"bm":0},{"ddd":0,"ind":5,"ty":2,"nm":"雲 3","refId":"image_4","sr":1,"ks":{"o":{"a":0,"k":100,"ix":11},"r":{"a":0,"k":0,"ix":10},"p":{"a":1,"k":[{"i":{"x":0.67,"y":1},"o":{"x":0.33,"y":0},"n":"0p67_1_0p33_0","t":0,"s":[991.545,365.48,0],"e":[999.795,359.98,0],"to":[2.16666674613953,-6.66666650772095,0],"ti":[0,0,0]},{"i":{"x":0.67,"y":1},"o":{"x":0.33,"y":0},"n":"0p67_1_0p33_0","t":40,"s":[999.795,359.98,0],"e":[991.545,365.48,0],"to":[0,0,0],"ti":[-1.05069065093994,3.2328941822052,0]},{"t":90.0000036657751}],"ix":2,"x":"var $bm_rt;\n$bm_rt = loopOut('cycle');"},"a":{"a":0,"k":[37.368,20.662,0],"ix":1},"s":{"a":0,"k":[100,100,100],"ix":6}},"ao":0,"ip":0,"op":180.00000733155,"st":0,"bm":0},{"ddd":0,"ind":6,"ty":2,"nm":"雲 2","refId":"image_4","sr":1,"ks":{"o":{"a":0,"k":100,"ix":11},"r":{"a":0,"k":0,"ix":10},"p":{"a":1,"k":[{"i":{"x":0.67,"y":1},"o":{"x":0.33,"y":0},"n":"0p67_1_0p33_0","t":0,"s":[813.045,121.48,0],"e":[805.17,127.73,0],"to":[-8.58333301544189,-1.91666662693024,0],"ti":[0.16666667163372,0.08333333581686,0]},{"i":{"x":0.67,"y":1},"o":{"x":0.33,"y":0},"n":"0p67_1_0p33_0","t":51,"s":[805.17,127.73,0],"e":[812.045,120.98,0],"to":[-0.16666667163372,-0.08333333581686,0],"ti":[0.19930939376354,5.23289442062378,0]},{"t":90.0000036657751}],"ix":2,"x":"var $bm_rt;\n$bm_rt = loopOut('cycle');"},"a":{"a":0,"k":[37.368,20.662,0],"ix":1},"s":{"a":0,"k":[100,100,100],"ix":6}},"ao":0,"ip":0,"op":180.00000733155,"st":0,"bm":0},{"ddd":0,"ind":7,"ty":2,"nm":"雲","refId":"image_4","sr":1,"ks":{"o":{"a":0,"k":100,"ix":11},"r":{"a":0,"k":0,"ix":10},"p":{"a":1,"k":[{"i":{"x":0.67,"y":1},"o":{"x":0.33,"y":0},"n":"0p67_1_0p33_0","t":0,"s":[407.545,233.48,0],"e":[421.545,224.98,0],"to":[2.16666674613953,-6.66666650772095,0],"ti":[0,0,0]},{"i":{"x":0.67,"y":1},"o":{"x":0.33,"y":0},"n":"0p67_1_0p33_0","t":45,"s":[421.545,224.98,0],"e":[407.545,233.48,0],"to":[0,0,0],"ti":[-1.05069065093994,3.2328941822052,0]},{"t":90.0000036657751}],"ix":2,"x":"var $bm_rt;\n$bm_rt = loopOut('cycle');"},"a":{"a":0,"k":[37.368,20.662,0],"ix":1},"s":{"a":0,"k":[100,100,100],"ix":6}},"ao":0,"ip":0,"op":180.00000733155,"st":0,"bm":0},{"ddd":0,"ind":8,"ty":2,"nm":"對話框-小","refId":"image_5","sr":1,"ks":{"o":{"a":1,"k":[{"i":{"x":[0.833],"y":[0.833]},"o":{"x":[0.167],"y":[0.167]},"n":["0p833_0p833_0p167_0p167"],"t":26,"s":[0],"e":[100]},{"i":{"x":[0.833],"y":[0.833]},"o":{"x":[0.167],"y":[0.167]},"n":["0p833_0p833_0p167_0p167"],"t":35,"s":[100],"e":[100]},{"i":{"x":[0.833],"y":[0.833]},"o":{"x":[0.167],"y":[0.167]},"n":["0p833_0p833_0p167_0p167"],"t":79,"s":[100],"e":[0]},{"i":{"x":[0.833],"y":[0.833]},"o":{"x":[0.167],"y":[0.167]},"n":["0p833_0p833_0p167_0p167"],"t":89,"s":[0],"e":[0]},{"i":{"x":[0.833],"y":[0.833]},"o":{"x":[0.167],"y":[0.167]},"n":["0p833_0p833_0p167_0p167"],"t":126,"s":[0],"e":[100]},{"i":{"x":[0.833],"y":[0.833]},"o":{"x":[0.167],"y":[0.167]},"n":["0p833_0p833_0p167_0p167"],"t":135,"s":[100],"e":[100]},{"i":{"x":[0.833],"y":[0.833]},"o":{"x":[0.167],"y":[0.167]},"n":["0p833_0p833_0p167_0p167"],"t":170,"s":[100],"e":[0]},{"t":180.00000733155}],"ix":11},"r":{"a":0,"k":0,"ix":10},"p":{"a":0,"k":[396.21,491.051,0],"ix":2},"a":{"a":0,"k":[40.01,42.326,0],"ix":1},"s":{"a":0,"k":[100,100,100],"ix":6}},"ao":0,"ip":0,"op":180.00000733155,"st":0,"bm":0},{"ddd":0,"ind":9,"ty":2,"nm":"對話框-大","refId":"image_6","sr":1,"ks":{"o":{"a":1,"k":[{"i":{"x":[0.833],"y":[0.833]},"o":{"x":[0.167],"y":[0.167]},"n":["0p833_0p833_0p167_0p167"],"t":21,"s":[1],"e":[100]},{"i":{"x":[0.833],"y":[0.833]},"o":{"x":[0.167],"y":[0.167]},"n":["0p833_0p833_0p167_0p167"],"t":30,"s":[100],"e":[100]},{"i":{"x":[0.833],"y":[0.833]},"o":{"x":[0.167],"y":[0.167]},"n":["0p833_0p833_0p167_0p167"],"t":79,"s":[100],"e":[0]},{"i":{"x":[0.833],"y":[0.833]},"o":{"x":[0.167],"y":[0.167]},"n":["0p833_0p833_0p167_0p167"],"t":89,"s":[0],"e":[1]},{"i":{"x":[0.833],"y":[0.833]},"o":{"x":[0.167],"y":[0.167]},"n":["0p833_0p833_0p167_0p167"],"t":121,"s":[1],"e":[100]},{"i":{"x":[0.833],"y":[0.833]},"o":{"x":[0.167],"y":[0.167]},"n":["0p833_0p833_0p167_0p167"],"t":130,"s":[100],"e":[100]},{"i":{"x":[0.833],"y":[0.833]},"o":{"x":[0.167],"y":[0.167]},"n":["0p833_0p833_0p167_0p167"],"t":170,"s":[100],"e":[0]},{"t":180.00000733155}],"ix":11},"r":{"a":0,"k":0,"ix":10},"p":{"a":0,"k":[434.941,389.088,0],"ix":2},"a":{"a":0,"k":[48.525,55.853,0],"ix":1},"s":{"a":0,"k":[100,100,100],"ix":6}},"ao":0,"ip":0,"op":180.00000733155,"st":0,"bm":0},{"ddd":0,"ind":10,"ty":2,"nm":"底","refId":"image_7","sr":1,"ks":{"o":{"a":0,"k":100,"ix":11},"r":{"a":0,"k":0,"ix":10},"p":{"a":0,"k":[689.069,443.104,0],"ix":2},"a":{"a":0,"k":[412.139,249.105,0],"ix":1},"s":{"a":0,"k":[100,100,100],"ix":6}},"ao":0,"ip":0,"op":180.00000733155,"st":0,"bm":0},{"ddd":0,"ind":11,"ty":2,"nm":"望遠鏡","refId":"image_8","sr":1,"ks":{"o":{"a":0,"k":100,"ix":11},"r":{"a":1,"k":[{"i":{"x":[0.59],"y":[1]},"o":{"x":[0.41],"y":[0]},"n":["0p59_1_0p41_0"],"t":0,"s":[0],"e":[-9.62]},{"i":{"x":[0.59],"y":[1]},"o":{"x":[0.41],"y":[0]},"n":["0p59_1_0p41_0"],"t":37,"s":[-9.62],"e":[-9.62]},{"i":{"x":[0.59],"y":[1]},"o":{"x":[0.41],"y":[0]},"n":["0p59_1_0p41_0"],"t":51,"s":[-9.62],"e":[5]},{"i":{"x":[0.59],"y":[1]},"o":{"x":[0.41],"y":[0]},"n":["0p59_1_0p41_0"],"t":74,"s":[5],"e":[0]},{"t":109.000004439661}],"ix":10,"x":"var $bm_rt;\n$bm_rt = loopOut('cycle');"},"p":{"a":0,"k":[718.887,197.027,0],"ix":2},"a":{"a":0,"k":[30.975,9.639,0],"ix":1},"s":{"a":0,"k":[100,100,100],"ix":6}},"ao":0,"ip":0,"op":180.00000733155,"st":0,"bm":0},{"ddd":0,"ind":12,"ty":2,"nm":"天秤桿","refId":"image_9","sr":1,"ks":{"o":{"a":0,"k":100,"ix":11},"r":{"a":1,"k":[{"i":{"x":[0.81],"y":[1]},"o":{"x":[0.19],"y":[0]},"n":["0p81_1_0p19_0"],"t":0,"s":[0],"e":[22]},{"i":{"x":[0.81],"y":[1]},"o":{"x":[0.19],"y":[0]},"n":["0p81_1_0p19_0"],"t":45,"s":[22],"e":[0]},{"t":90.0000036657751}],"ix":10,"x":"var $bm_rt;\n$bm_rt = loopOut('cycle');"},"p":{"a":0,"k":[571.868,251.402,0],"ix":2},"a":{"a":0,"k":[36.257,10.382,0],"ix":1},"s":{"a":0,"k":[100,100,100],"ix":6}},"ao":0,"ip":0,"op":180.00000733155,"st":0,"bm":0},{"ddd":0,"ind":13,"ty":2,"nm":"天秤男","refId":"image_10","sr":1,"ks":{"o":{"a":0,"k":100,"ix":11},"r":{"a":0,"k":0,"ix":10},"p":{"a":1,"k":[{"i":{"x":0.81,"y":1},"o":{"x":0.19,"y":0},"n":"0p81_1_0p19_0","t":0,"s":[603.954,262.581,0],"e":[603.954,277.081,0],"to":[0,2.41666674613953,0],"ti":[0,0,0]},{"i":{"x":0.81,"y":1},"o":{"x":0.19,"y":0},"n":"0p81_1_0p19_0","t":45,"s":[603.954,277.081,0],"e":[603.954,262.581,0],"to":[0,0,0],"ti":[0,2.41666674613953,0]},{"t":90.0000036657751}],"ix":2,"x":"var $bm_rt;\n$bm_rt = loopOut('cycle');"},"a":{"a":0,"k":[14.203,21.162,0],"ix":1},"s":{"a":0,"k":[100,100,100],"ix":6}},"ao":0,"ip":0,"op":180.00000733155,"st":0,"bm":0},{"ddd":0,"ind":14,"ty":2,"nm":"天秤女","refId":"image_11","sr":1,"ks":{"o":{"a":0,"k":100,"ix":11},"r":{"a":0,"k":0,"ix":10},"p":{"a":1,"k":[{"i":{"x":0.81,"y":1},"o":{"x":0.19,"y":0},"n":"0p81_1_0p19_0","t":0,"s":[539.196,277.515,0],"e":[539.196,266.515,0],"to":[0,-1.83333337306976,0],"ti":[0,0,0]},{"i":{"x":0.81,"y":1},"o":{"x":0.19,"y":0},"n":"0p81_1_0p19_0","t":45,"s":[539.196,266.515,0],"e":[539.196,277.515,0],"to":[0,0,0],"ti":[0,-1.83333337306976,0]},{"t":90.0000036657751}],"ix":2,"x":"var $bm_rt;\nloopOut('cycle');\n$bm_rt = loopOut('cycle');"},"a":{"a":0,"k":[14.202,21.438,0],"ix":1},"s":{"a":0,"k":[100,100,100],"ix":6}},"ao":0,"ip":0,"op":180.00000733155,"st":0,"bm":0}]}],"layers":[{"ddd":0,"ind":1,"ty":0,"nm":"首頁動畫","refId":"comp_0","sr":1,"ks":{"o":{"a":0,"k":100,"ix":11},"r":{"a":0,"k":0,"ix":10},"p":{"a":1,"k":[{"i":{"x":0.67,"y":1},"o":{"x":0.33,"y":0},"n":"0p67_1_0p33_0","t":0,"s":[640,716,0],"e":[640,706,0],"to":[0,-1.66666662693024,0],"ti":[0,0,0]},{"i":{"x":0.67,"y":1},"o":{"x":0.33,"y":0},"n":"0p67_1_0p33_0","t":45,"s":[640,706,0],"e":[640,716,0],"to":[0,0,0],"ti":[0,-1.66666662693024,0]},{"t":90.0000036657751}],"ix":2,"x":"var $bm_rt;\n$bm_rt = loopOut('cycle');"},"a":{"a":0,"k":[700,473.5,0],"ix":1},"s":{"a":0,"k":[145,145,100],"ix":6}},"ao":0,"w":1400,"h":947,"ip":0,"op":180.00000733155,"st":0,"bm":0}]}